datasets/__init__.py
examples/__init__.py
examples/demo_usage.py
models/__init__.py
models/ad_conversion.py
models/advanced_mmm.py
models/clv_prediction.py
models/demand_forecasting.py
models/geo_level_mmm.py
models/model_validation.py
models/multi_armed_bandit.py
models/pareto_k_diagnostics.py
models/seasonality.py
models/ucm_model.py
bayesmarketing_mmm-0.0.1.dist-info/LICENCE.txt
bayesmarketing_mmm-0.0.1.dist-info/METADATA
bayesmarketing_mmm-0.0.1.dist-info/WHEEL
bayesmarketing_mmm-0.0.1.dist-info/top_level.txt
bayesmarketing_mmm-0.0.1.dist-info/RECORD
